db_cache/__init__.py
db_cache/db_cache.py
db_cache-0.1.2.dist-info/DESCRIPTION.rst
db_cache-0.1.2.dist-info/METADATA
db_cache-0.1.2.dist-info/RECORD
db_cache-0.1.2.dist-info/WHEEL
db_cache-0.1.2.dist-info/metadata.json
db_cache-0.1.2.dist-info/top_level.txt
