Metadata-Version: 2.0
Name: db-cache
Version: 0.1.2
Summary: database caching for dynamic programming
Home-page: https://github.com/bchiang2/db_cache
Author: Benjamin Chiang
Author-email: aroy@alum.mit.edu
License: MIT license
Keywords: db_cache
Platform: UNKNOWN
Classifier: Development Status :: 2 - Pre-Alpha
Classifier: Intended Audience :: Developers
Classifier: License :: OSI Approved :: MIT License
Classifier: Natural Language :: English
Classifier: Programming Language :: Python :: 2
Classifier: Programming Language :: Python :: 2.6
Classifier: Programming Language :: Python :: 2.7
Classifier: Programming Language :: Python :: 3
Classifier: Programming Language :: Python :: 3.3
Classifier: Programming Language :: Python :: 3.4
Classifier: Programming Language :: Python :: 3.5
Requires-Dist: psycopg2
